mitotnt/__init__.py
mitotnt/mito_segmenter.py
mitotnt/network_tracker.py
mitotnt/skeletonized_mito.py
mitotnt/tracked_mito.py
mitotnt/visualizer.py
mitotnt-0.2.0.dist-info/licenses/License
mitotnt-0.2.0.dist-info/METADATA
mitotnt-0.2.0.dist-info/WHEEL
mitotnt-0.2.0.dist-info/top_level.txt
mitotnt-0.2.0.dist-info/RECORD
