Metadata-Version: 2.4
Name: mitotnt
Version: 0.2.0
Summary: Python toolkit for analyzing temporal dynamics of mitochondrial networks
Author-email: Zachary Wang <ziw056@ucsd.edu>
License: BSD 3-Clause License
Project-URL: Homepage, https://mitotnt.org
Project-URL: Documentation, https://pylattice.github.io/MitoTNT/
Requires-Python: >=3.9
License-File: License
Requires-Dist: numpy>=1.22
Requires-Dist: scipy>=1.8
Requires-Dist: pandas>=1.4
Requires-Dist: matplotlib>=3.5
Requires-Dist: scikit-image>=0.19
Requires-Dist: tifffile
Requires-Dist: igraph
Requires-Dist: fastdist
Requires-Dist: aicsimageio
Requires-Dist: tqdm
Requires-Dist: numba
Requires-Dist: jupyter
Provides-Extra: dev
Requires-Dist: pytest; extra == "dev"
Requires-Dist: black; extra == "dev"
Requires-Dist: flake8; extra == "dev"
Dynamic: license-file
